django_botbench/__init__.py
django_botbench/apps.py
django_botbench/asgi.py
django_botbench/bots.py
django_botbench/consumers.py
django_botbench/routing.py
django_botbench/urls.py
django_botbench/views.py
django_botbench/static/css/botbench-chat-embed.css
django_botbench/static/js/botbench-chat-embed.js
django_botbench/static/js/chat.js
django_botbench/static/js/markdown-parser.js
django_botbench/templates/chat/chat_embed.html
django_botbench/templates/chat/embed_example.html
django_botbench-0.1.5.dist-info/licenses/LICENSE.txt
django_botbench-0.1.5.dist-info/METADATA
django_botbench-0.1.5.dist-info/WHEEL
django_botbench-0.1.5.dist-info/top_level.txt
django_botbench-0.1.5.dist-info/RECORD
