Metadata-Version: 2.4
Name: django-botbench
Version: 0.1.5
Summary: A Django app for connecting RoboOp-powered chatbots to the web.
Author-email: Alan Rowarth <alan@codex.cx>
License-Expression: MIT
Project-URL: Repository, https://github.com/ajrowr/BotBench
Classifier: Development Status :: 2 - Pre-Alpha
Classifier: Framework :: Django
Classifier: Framework :: Django :: 4.0
Classifier: Framework :: Django :: 4.1
Classifier: Framework :: Django :: 4.2
Classifier: Framework :: Django :: 5
Classifier: Framework :: Django :: 5.0
Classifier: Framework :: Django :: 5.1
Classifier: Framework :: Django :: 5.2
Requires-Python: >=3.10
License-File: LICENSE.txt
Requires-Dist: channels-redis>=4.3.0
Requires-Dist: channels[daphne]>=4.3.1
Requires-Dist: roboop>=0.6.2
Dynamic: license-file
